{
  "apiVersion": "apiextensions.k8s.io/v1beta1",
  "kind": "CustomResourceDefinition",
  "metadata": {
    "creationTimestamp": "2019-09-09T16:04:49Z",
    "generation": 1,
    "name": "physicalstatefulclusters.operator.confluent.cloud",
    "resourceVersion": "1239",
    "selfLink": "/apis/apiextensions.k8s.io/v1beta1/customresourcedefinitions/physicalstatefulclusters.operator.confluent.cloud",
    "uid": "649a86ea-6c51-4935-b5ea-06ddc4a74ffa"
  },
  "spec": {
    "conversion": {
      "strategy": "None"
    },
    "group": "operator.confluent.cloud",
    "names": {
      "kind": "PhysicalStatefulCluster",
      "listKind": "PhysicalStatefulClusterList",
      "plural": "physicalstatefulclusters",
      "shortNames": [
        "psc"
      ],
      "singular": "physicalstatefulcluster"
    },
    "preserveUnknownFields": true,
    "scope": "Namespaced",
    "version": "v1",
    "versions": [
      {
        "name": "v1",
        "served": true,
        "storage": true
      }
    ]
  },
  "status": {
    "acceptedNames": {
      "kind": "PhysicalStatefulCluster",
      "listKind": "PhysicalStatefulClusterList",
      "plural": "physicalstatefulclusters",
      "shortNames": [
        "psc"
      ],
      "singular": "physicalstatefulcluster"
    },
    "conditions": [
      {
        "lastTransitionTime": "2019-09-09T16:04:49Z",
        "message": "no conflicts found",
        "reason": "NoConflicts",
        "status": "True",
        "type": "NamesAccepted"
      },
      {
        "lastTransitionTime": null,
        "message": "the initial names have been accepted",
        "reason": "InitialNamesAccepted",
        "status": "True",
        "type": "Established"
      }
    ],
    "storedVersions": [
      "v1"
    ]
  }
}
